riversand/__init__.py
riversand/_version.py
riversand/calc.py
riversand/geospatial.py
riversand/params.py
riversand/plot.py
riversand/utils.py
riversand/xml.py
riversand-1.4.dist-info/licenses/LICENSE
riversand-1.4.dist-info/METADATA
riversand-1.4.dist-info/WHEEL
riversand-1.4.dist-info/top_level.txt
riversand-1.4.dist-info/RECORD
