Metadata-Version: 2.4
Name: riversand
Version: 1.4
Summary: Catchmentwide erosion rate calculator
Home-page: https://github.com/kstueb/riversand
Author: Konstanze Stuebner
Author-email: kstueb@gmail.com
Classifier: Programming Language :: Python
Classifier: Programming Language :: Python :: 3
Classifier: License :: OSI Approved :: GNU General Public License v3 (GPLv3)
Classifier: Operating System :: OS Independent
Classifier: Development Status :: 4 - Beta
Classifier: Intended Audience :: Science/Research
Classifier: Intended Audience :: Education
Classifier: Topic :: Education
Classifier: Topic :: Scientific/Engineering
Classifier: Topic :: Scientific/Engineering :: GIS
License-File: LICENSE
Requires-Dist: numpy
Requires-Dist: scipy
Requires-Dist: pandas
Requires-Dist: xarray
Requires-Dist: rasterio
Requires-Dist: pyproj
Requires-Dist: fiona
Requires-Dist: matplotlib
Requires-Dist: odfpy
Requires-Dist: openpyxl
Dynamic: author
Dynamic: author-email
Dynamic: classifier
Dynamic: description
Dynamic: description-content-type
Dynamic: home-page
Dynamic: license-file
Dynamic: requires-dist
Dynamic: summary
